<?xml version="1.0" encoding="utf-8"?>
<FractalPresets xmlns:xsi="http://www.w3.org/2001/XMLSchema-instance" xmlns:xsd="http://www.w3.org/2001/XMLSchema">
  <seconds>3</seconds>
  <depth>1</depth>
  <attackDecay>100</attackDecay>
  <minWaves>10</minWaves>
  <maxWaves>0</maxWaves>
  <mod>0</mod>
  <oscillator>0</oscillator>
  <baseFreq>400</baseFreq>
  <amplitude>0.1</amplitude>
  <sample>unsure</sample>
  <earProtection>false</earProtection>
  <cutoffHigh>1000</cutoffHigh>
  <cutoffLow>200</cutoffLow>
  <name>sierpinsky_clouds</name>
  <transformations>
    <Transformation>
      <start>0</start>
      <end>0.5</end>
      <multFrequency>3</multFrequency>
      <color />
    </Transformation>
    <Transformation>
      <start>0.5</start>
      <end>1</end>
      <multFrequency>4</multFrequency>
      <color />
    </Transformation>
    <Transformation>
      <start>0.25</start>
      <end>0.5</end>
      <multFrequency>3</multFrequency>
      <color />
    </Transformation>
    <Transformation>
      <start>0.5</start>
      <end>0.25</end>
      <multFrequency>2</multFrequency>
      <color />
    </Transformation>
  </transformations>
</FractalPresets>